cyvi.cpython-39-darwin.so
cyflashtext/__init__.py
cyflashtext/cyflashtext.py
cyflashtext-0.0.5.dist-info/LICENSE
cyflashtext-0.0.5.dist-info/METADATA
cyflashtext-0.0.5.dist-info/WHEEL
cyflashtext-0.0.5.dist-info/top_level.txt
cyflashtext-0.0.5.dist-info/RECORD
