Metadata-Version: 2.1
Name: cyflashtext
Version: 0.0.5
Summary: Python flashtext with c++ backend
Home-page: https://github.com/NgHoangDat/cyflashtext
Author: nghoangdat
Author-email: 18.hoang.dat.12@gmail.com
Classifier: Programming Language :: Python :: 3
Classifier: License :: OSI Approved :: MIT License
Classifier: Operating System :: OS Independent
Classifier: Topic :: Text Processing :: Linguistic
Requires-Python: >=3.6
License-File: LICENSE
